hstransform/__init__.py
hstransform/hstransform.py
tests/__init__.py
tests/test_hstransform.py
HSTransform-0.1.1.dist-info/METADATA
HSTransform-0.1.1.dist-info/WHEEL
HSTransform-0.1.1.dist-info/top_level.txt
HSTransform-0.1.1.dist-info/RECORD
