Metadata-Version: 2.1
Name: HSTransform
Version: 0.1.1
Summary: A Package to Compute S-transform with Hyperbolic Window
Home-page: https://github.com/nvlinhvn/HSTransform
Author: Linh V Nguyen
Author-email: linhvietnguyen.ee@gmail.com
License: MIT
Classifier: Development Status :: 4 - Beta
Classifier: License :: OSI Approved :: MIT License
Classifier: Programming Language :: Python :: 3.10
Requires-Python: >=3.10
Requires-Dist: numpy (>=1.21.2)
Requires-Dist: scipy (>=1.7.1)
Requires-Dist: pandas (>=1.3.3)
Requires-Dist: pytest (>=6.2.5)
